swapi/__init__.py
swapi/exceptions.py
swapi/models.py
swapi/settings.py
swapi/swapi.py
swapi/utils.py
swapi-0.1.3.dist-info/DESCRIPTION.rst
swapi-0.1.3.dist-info/METADATA
swapi-0.1.3.dist-info/metadata.json
swapi-0.1.3.dist-info/RECORD
swapi-0.1.3.dist-info/top_level.txt
swapi-0.1.3.dist-info/WHEEL
