Metadata-Version: 1.1
Name: swapi
Version: 0.1.3
Summary: A Python helper library for swapi.co - the Star Wars API
Home-page: https://github.com/phalt/swapi-python
Author: Paul Hallett
Author-email: paulandrewhallett@gmail.com
License: BSD
Keywords: swapi
Platform: UNKNOWN
Classifier: Development Status :: 2 - Pre-Alpha
Classifier: Intended Audience :: Developers
Classifier: License :: OSI Approved :: BSD License
Classifier: Natural Language :: English
Classifier: Programming Language :: Python :: 2
Classifier: Programming Language :: Python :: 2.6
Classifier: Programming Language :: Python :: 2.7
Classifier: Programming Language :: Python :: 3
Classifier: Programming Language :: Python :: 3.3
Classifier: Programming Language :: Python :: 3.4
